jsj/__init__.py
jsj-0.3.4.dist-info/METADATA
jsj-0.3.4.dist-info/WHEEL
jsj-0.3.4.dist-info/licenses/LICENSE
jsj-0.3.4.dist-info/RECORD
