Metadata-Version: 2.3
Name: jsj
Version: 0.3.4
Summary: JavaScript QoL for JSON in python
Project-URL: Homepage, https://github.com/some1and2-XC/jsj
Project-URL: GitHub, https://github.com/some1and2-XC/jsj
Author: Mark Tobin
License-File: LICENSE
Classifier: Operating System :: OS Independent
Classifier: Programming Language :: Python :: 3
Requires-Python: >=3.12
Requires-Dist: lindex
Requires-Dist: requests
Requires-Dist: typing-extensions
